test_python_project/functions.py
testpythonproject-0.2.0.dist-info/licenses/LICENSE
testpythonproject-0.2.0.dist-info/METADATA
testpythonproject-0.2.0.dist-info/WHEEL
testpythonproject-0.2.0.dist-info/entry_points.txt
testpythonproject-0.2.0.dist-info/top_level.txt
testpythonproject-0.2.0.dist-info/RECORD
