Metadata-Version: 2.4
Name: TestPythonProject
Version: 0.2.0
Summary: Test python project
Author-email: Geode-solutions <contact@geode-solutions.com>
Project-URL: Homepage, https://github.com/Geode-solutions/2025MilanoBicocca
Project-URL: Bug Tracker, https://github.com/Geode-solutions/2025MilanoBicocca/issues
Classifier: Programming Language :: Python :: 3
Classifier: License :: OSI Approved :: MIT License
Classifier: Operating System :: OS Independent
Requires-Python: >=3.8
License-File: LICENSE
Requires-Dist: opengeode-core==15.18.0
Dynamic: license-file
